{
	"type": "FeatureCollection",
	"features": [
		{
			"type": "Feature",
			"geometry": {
				"type": "Point",
				"coordinates": [
					16.36775,
					48.246978
				]
			},
			"properties": {
				"Place": "Universidad de agronomía de Viena",
				
				"temp_2024-04-04T12:04:12Z": 20.25
			}
		}
	]
}